YTagFinder/__init__.py
YTagFinder/ytagfinder.py
YTagFinder-0.0.2.dist-info/METADATA
YTagFinder-0.0.2.dist-info/WHEEL
YTagFinder-0.0.2.dist-info/top_level.txt
YTagFinder-0.0.2.dist-info/RECORD
