Metadata-Version: 2.1
Name: YTagFinder
Version: 0.0.2
Summary: Simple Module for fetching youtube tags
Home-page: https://github.com/Tina-rt/ytagfinder
Author: Tina Ratolojanahary
Author-email: <rtinahubert@gmail.com>
License: UNKNOWN
Keywords: python,youtube tags
Platform: UNKNOWN
Classifier: Development Status :: 3 - Alpha
Classifier: Intended Audience :: Education
Classifier: Programming Language :: Python :: 2
Classifier: Programming Language :: Python :: 3
Classifier: Operating System :: MacOS :: MacOS X
Classifier: Operating System :: Microsoft :: Windows
Requires-Dist: bs4
Requires-Dist: requests
